mkdocs_audiotag/__init__.py
mkdocs_audiotag/plugin.py
mkdocs_audiotag-0.1.1.dist-info/licenses/LICENSE
mkdocs_audiotag-0.1.1.dist-info/METADATA
mkdocs_audiotag-0.1.1.dist-info/WHEEL
mkdocs_audiotag-0.1.1.dist-info/entry_points.txt
mkdocs_audiotag-0.1.1.dist-info/top_level.txt
mkdocs_audiotag-0.1.1.dist-info/RECORD
