Metadata-Version: 2.4
Name: mkdocs-audiotag
Version: 0.1.1
Summary: MkDocs plugin for simple audio file embedding
Author: Anders Eskildsen
License-Expression: MIT
Project-URL: Homepage, https://github.com/aeskildsen/mkdocs-audiotag
Classifier: Programming Language :: Python :: 3
Classifier: Framework :: MkDocs
Classifier: Operating System :: OS Independent
Classifier: Development Status :: 3 - Alpha
Classifier: Topic :: Multimedia :: Sound/Audio
Requires-Python: >=3.8
License-File: LICENSE
Requires-Dist: mkdocs>=1.6.1
Dynamic: license-file
